devanalyst/__init__.py
devanalyst/jupyter_nb_importer.py
devanalyst/metrics/ProductivityMetrics.ipynb
devanalyst/metrics/__init__.py
devanalyst/metrics/scm_based_metrics.ipynb
devanalyst/metrics/.ipynb_checkpoints/ProductivityMetrics-checkpoint.ipynb
devanalyst/metrics/.ipynb_checkpoints/scm_based_metrics-checkpoint.ipynb
devanalyst/metrics/tests/all_productivity_test.py
devanalyst/metrics/tests/test_productivity.ipynb
devanalyst/metrics/tests/.ipynb_checkpoints/test_productivity-checkpoint.ipynb
devanalyst/pilots/couplingPilot.ipynb
devanalyst/pilots/workStealingTest.ipynb
devanalyst/pilots/.ipynb_checkpoints/couplingPilot-checkpoint.ipynb
devanalyst/pilots/.ipynb_checkpoints/metrics_pilots-checkpoint.ipynb
devanalyst/pilots/.ipynb_checkpoints/workStealingTest-checkpoint.ipynb
devanalyst/resources/coupling/CodeCoupling.xlsx
devanalyst/resources/simulation/Team.xlsx
devanalyst/resources/tests/metrics/productivity.test_drag.Burnout_with_drag_EXPECTED.csv
devanalyst/resources/tests/metrics/productivity.test_drag.Burnout_without_drag_EXPECTED.csv
devanalyst/resources/tests/metrics/productivity.test_drag.Commits_all_with_drag_EXPECTED.csv
devanalyst/resources/tests/metrics/productivity.test_drag.Commits_all_without_drag_EXPECTED.csv
devanalyst/resources/tests/metrics/productivity.test_drag.Commits_bugs_with_drag_EXPECTED.csv
devanalyst/resources/tests/metrics/productivity.test_drag.Commits_bugs_without_drag_EXPECTED.csv
devanalyst/resources/tests/metrics/productivity.test_drag.Commits_impl_with_drag_EXPECTED.csv
devanalyst/resources/tests/metrics/productivity.test_drag.Commits_impl_without_drag_EXPECTED.csv
devanalyst/resources/tests/metrics/productivity.test_drag.Entries_with_drag_EXPECTED.csv
devanalyst/resources/tests/metrics/productivity.test_drag.Entries_without_drag_EXPECTED.csv
devanalyst/resources/tests/metrics/productivity.test_drag.Impact_EXPECTED.csv
devanalyst/resources/tests/metrics/productivity.test_simple.meritocratic_EXPECTED.csv
devanalyst-0.3.0rc1.dist-info/LICENSE
devanalyst-0.3.0rc1.dist-info/METADATA
devanalyst-0.3.0rc1.dist-info/WHEEL
devanalyst-0.3.0rc1.dist-info/top_level.txt
devanalyst-0.3.0rc1.dist-info/RECORD
