Metadata-Version: 2.1
Name: devanalyst
Version: 0.3.0rc1
Summary: Tools to simulate and analyze software development lifecycles
Home-page: http://github.com/ChateauClaudia-Labs/devanalyst
Author: Alejandro Hernandez
Author-email: alejandro@chateauclaudia-labs.com
License: MIT
Keywords: development efficiency analysis process simulation
Platform: UNKNOWN
Classifier: Programming Language :: Python :: 3.7
Classifier: License :: OSI Approved :: MIT License
Classifier: Operating System :: OS Independent
Classifier: Development Status :: 2 - Pre-Alpha
Classifier: Topic :: Software Development
Requires-Dist: pandas
Requires-Dist: numpy
Requires-Dist: IPython
Requires-Dist: nbformat
